[
    {
        "lastName": "Tirukkovellour",
        "firstName": "Santhosh",
        "emailAddress": "santhosh.tirukkovellour@gmail.com",
        "score": 18,
        "timeInSeconds": 695,
        "time": "00:11:35",
        "numberOfTimesRespondentsLeftQuestionPage": "1"
    },
    {
        "lastName": "MB",
        "firstName": "Raghavendra",
        "emailAddress": "raghavendra.mb@maersk.com",
        "score": 17,
        "timeInSeconds": 498,
        "time": "00:08:18",
        "numberOfTimesRespondentsLeftQuestionPage": "0"
    },
    {
        "lastName": "Roy",
        "firstName": "Feny",
        "emailAddress": "starkroy1999@gmail.com",
        "score": 17,
        "timeInSeconds": 633,
        "time": "00:10:33",
        "numberOfTimesRespondentsLeftQuestionPage": "0"
    },
    {
        "lastName": "Maan",
        "firstName": "Beetu",
        "emailAddress": "beetumaan19@gmail.com",
        "score": 15,
        "timeInSeconds": 525,
        "time": "00:08:45",
        "numberOfTimesRespondentsLeftQuestionPage": "0"
    },
    {
        "lastName": "Khanapurkar",
        "firstName": "Amol",
        "emailAddress": "Amol.khanapurkar@tcs.com",
        "score": 14,
        "timeInSeconds": 895,
        "time": "00:14:55",
        "numberOfTimesRespondentsLeftQuestionPage": "0"
    },
    {
        "lastName": "Burewar",
        "firstName": "Shubham",
        "emailAddress": "shubham.ja96@gmail.com",
        "score": 14,
        "timeInSeconds": 428,
        "time": "00:07:08",
        "numberOfTimesRespondentsLeftQuestionPage": "0"
    },
    {
        "lastName": "Patil",
        "firstName": "Sourabh",
        "emailAddress": "sourabhpatil678@gmail.com",
        "score": 13,
        "timeInSeconds": 774,
        "time": "00:12:54",
        "numberOfTimesRespondentsLeftQuestionPage": "0"
    },
    {
        "lastName": "Vaidya",
        "firstName": "Sarang",
        "emailAddress": "sarang.vaidya@mendix.com",
        "score": 12,
        "timeInSeconds": 794,
        "time": "00:13:14",
        "numberOfTimesRespondentsLeftQuestionPage": "2"
    },
    {
        "lastName": "KUMARI",
        "firstName": "NITA",
        "emailAddress": "nita2shine@yahoo.co.in",
        "score": 12,
        "timeInSeconds": 805,
        "time": "00:13:25",
        "numberOfTimesRespondentsLeftQuestionPage": "2"
    },
    {
        "lastName": "Sharma",
        "firstName": "Divyansh",
        "emailAddress": "divyansh2593@gmail.com",
        "score": 11,
        "timeInSeconds": 99,
        "time": "00:01:39",
        "numberOfTimesRespondentsLeftQuestionPage": "1"
    },
    {
        "lastName": "Sn",
        "firstName": "Vijay",
        "emailAddress": "vjay.sn@gmail.com",
        "score": 10,
        "timeInSeconds": 402,
        "time": "00:06:42",
        "numberOfTimesRespondentsLeftQuestionPage": "0"
    },
    {
        "lastName": "Sistla",
        "firstName": "Bhaskar",
        "emailAddress": "bhaskar.sistla@gmail.com",
        "score": 9,
        "timeInSeconds": 900,
        "time": "00:15:00",
        "numberOfTimesRespondentsLeftQuestionPage": "5"
    },
    {
        "lastName": "Rapeti",
        "firstName": "Siva",
        "emailAddress": "sivarank@gmail.com",
        "score": 9,
        "timeInSeconds": 877,
        "time": "00:14:37",
        "numberOfTimesRespondentsLeftQuestionPage": "1"
    },
    {
        "lastName": "George",
        "firstName": "Elizabeth",
        "emailAddress": "elizabethgeorge1998@gmail.com",
        "score": 9,
        "timeInSeconds": 654,
        "time": "00:10:54",
        "numberOfTimesRespondentsLeftQuestionPage": "1"
    },
    {
        "lastName": "R.B",
        "firstName": "Pavan",
        "emailAddress": "pavanrb5007@gmail.com",
        "score": 9,
        "timeInSeconds": 337,
        "time": "00:05:37",
        "numberOfTimesRespondentsLeftQuestionPage": "0"
    },
    {
        "lastName": "Gupta",
        "firstName": "Priyank",
        "emailAddress": "2707.priyank@gmail.com",
        "score": 9,
        "timeInSeconds": 584,
        "time": "00:09:44",
        "numberOfTimesRespondentsLeftQuestionPage": "0"
    },
    {
        "lastName": "Javadekar",
        "firstName": "Vaibhav",
        "emailAddress": "vabsjava@gmail.com",
        "score": 9,
        "timeInSeconds": 636,
        "time": "00:10:36",
        "numberOfTimesRespondentsLeftQuestionPage": "0"
    },
    {
        "lastName": "Nanduri",
        "firstName": "Teja",
        "emailAddress": "godsandmen2016@gmail.com",
        "score": 9,
        "timeInSeconds": 442,
        "time": "00:07:22",
        "numberOfTimesRespondentsLeftQuestionPage": "0"
    },
    {
        "lastName": "J",
        "firstName": "Uma Kanth",
        "emailAddress": "uma_kanth@outlook.com",
        "score": 9,
        "timeInSeconds": 900,
        "time": "00:15:00",
        "numberOfTimesRespondentsLeftQuestionPage": "0"
    },
    {
        "lastName": "Singh",
        "firstName": "Ankur",
        "emailAddress": "ankur.singh1000@gmail.com",
        "score": 8,
        "timeInSeconds": 505,
        "time": "00:08:25",
        "numberOfTimesRespondentsLeftQuestionPage": "0"
    },
    {
        "lastName": "Singhal",
        "firstName": "Soniya",
        "emailAddress": "Soniyasinghal08@gmail.com",
        "score": 8,
        "timeInSeconds": 527,
        "time": "00:08:47",
        "numberOfTimesRespondentsLeftQuestionPage": "0"
    },
    {
        "lastName": "Sane",
        "firstName": "Venkata Lokeswara Reddy",
        "emailAddress": "loki.sane@outreach.io",
        "score": 7,
        "timeInSeconds": 222,
        "time": "00:03:42",
        "numberOfTimesRespondentsLeftQuestionPage": "0"
    },
    {
        "lastName": "Mittal",
        "firstName": "Manik",
        "emailAddress": "manik.mittal@ushur.com",
        "score": 7,
        "timeInSeconds": 564,
        "time": "00:09:24",
        "numberOfTimesRespondentsLeftQuestionPage": "0"
    },
    {
        "lastName": "Sharma",
        "firstName": "Chandan",
        "emailAddress": "css08740@gmail.com",
        "score": 6,
        "timeInSeconds": 272,
        "time": "00:04:32",
        "numberOfTimesRespondentsLeftQuestionPage": "2"
    },
    {
        "lastName": "Valecha",
        "firstName": "Garima",
        "emailAddress": "garimavalecha4@gmail.com",
        "score": 6,
        "timeInSeconds": 139,
        "time": "00:02:19",
        "numberOfTimesRespondentsLeftQuestionPage": "1"
    },
    {
        "lastName": "Chauhan",
        "firstName": "Grijesh",
        "emailAddress": "Grijesh.Mnit@gmail.com",
        "score": 6,
        "timeInSeconds": 900,
        "time": "00:15:00",
        "numberOfTimesRespondentsLeftQuestionPage": "0"
    },
    {
        "lastName": "Gupta",
        "firstName": "Isha",
        "emailAddress": "erishagupta1408@gmail.com",
        "score": 6,
        "timeInSeconds": 136,
        "time": "00:02:16",
        "numberOfTimesRespondentsLeftQuestionPage": "0"
    },
    {
        "lastName": "Kamath",
        "firstName": "Hari",
        "emailAddress": "vishal.hari26@gmail.com",
        "score": 5,
        "timeInSeconds": 899,
        "time": "00:14:59",
        "numberOfTimesRespondentsLeftQuestionPage": "2"
    },
    {
        "lastName": "Chikara",
        "firstName": "Shelly",
        "emailAddress": "Shellychikara18@gmail.com",
        "score": 5,
        "timeInSeconds": 226,
        "time": "00:03:46",
        "numberOfTimesRespondentsLeftQuestionPage": "2"
    },
    {
        "lastName": "Ghate",
        "firstName": "Chetan",
        "emailAddress": "Chetanghate97@gmail.com",
        "score": 5,
        "timeInSeconds": 167,
        "time": "00:02:47",
        "numberOfTimesRespondentsLeftQuestionPage": "1"
    },
    {
        "lastName": "Indoria",
        "firstName": "Naveen",
        "emailAddress": "naveenindoria1103@gmail.com",
        "score": 5,
        "timeInSeconds": 816,
        "time": "00:13:36",
        "numberOfTimesRespondentsLeftQuestionPage": "0"
    },
    {
        "lastName": "kumar",
        "firstName": "Shivam",
        "emailAddress": "kshivam0296@gmail.com",
        "score": 5,
        "timeInSeconds": 499,
        "time": "00:08:19",
        "numberOfTimesRespondentsLeftQuestionPage": "0"
    },
    {
        "lastName": "Thondur",
        "firstName": "Adeppa",
        "emailAddress": "adeppa.t@gmail.com",
        "score": 5,
        "timeInSeconds": 91,
        "time": "00:01:31",
        "numberOfTimesRespondentsLeftQuestionPage": "0"
    },
    {
        "lastName": "Kulkarni",
        "firstName": "Amarendra",
        "emailAddress": "Amarendrakulkarni@gmail.com",
        "score": 5,
        "timeInSeconds": 285,
        "time": "00:04:45",
        "numberOfTimesRespondentsLeftQuestionPage": "0"
    },
    {
        "lastName": "KN",
        "firstName": "Vardharajulu",
        "emailAddress": "raajulu@gmail.com",
        "score": 4,
        "timeInSeconds": 900,
        "time": "00:15:00",
        "numberOfTimesRespondentsLeftQuestionPage": "3"
    },
    {
        "lastName": "Shah",
        "firstName": "Ansul",
        "emailAddress": "ansul.shah93@gmail.com",
        "score": 4,
        "timeInSeconds": 605,
        "time": "00:10:05",
        "numberOfTimesRespondentsLeftQuestionPage": "1"
    },
    {
        "lastName": "I",
        "firstName": "Indra",
        "emailAddress": "indra.manda@gmail.com",
        "score": 3,
        "timeInSeconds": 900,
        "time": "00:15:00",
        "numberOfTimesRespondentsLeftQuestionPage": "1"
    },
    {
        "lastName": "Bhatnagar",
        "firstName": "Geetika",
        "emailAddress": "Geetika2795@gmail.com",
        "score": 3,
        "timeInSeconds": 110,
        "time": "00:01:50",
        "numberOfTimesRespondentsLeftQuestionPage": "1"
    },
    {
        "lastName": "Bagal",
        "firstName": "Pankaj",
        "emailAddress": "pankajsbagal@gmail.com",
        "score": 3,
        "timeInSeconds": 324,
        "time": "00:05:24",
        "numberOfTimesRespondentsLeftQuestionPage": "1"
    },
    {
        "lastName": "Banerjee",
        "firstName": "Susmit",
        "emailAddress": "susmit.b1@gmail.com",
        "score": 3,
        "timeInSeconds": 143,
        "time": "00:02:23",
        "numberOfTimesRespondentsLeftQuestionPage": "0"
    },
    {
        "lastName": "Wadhwa",
        "firstName": "Neha",
        "emailAddress": "nh.wadhwa99@gmail.com",
        "score": 3,
        "timeInSeconds": 181,
        "time": "00:03:01",
        "numberOfTimesRespondentsLeftQuestionPage": "0"
    },
    {
        "lastName": "Anupam",
        "firstName": "Aman",
        "emailAddress": "amananupam333@gmail.com",
        "score": 2,
        "timeInSeconds": 900,
        "time": "00:15:00",
        "numberOfTimesRespondentsLeftQuestionPage": "5"
    },
    {
        "lastName": "Choudhary",
        "firstName": "Abhishek",
        "emailAddress": "Abchoudhary@paypal.com",
        "score": 2,
        "timeInSeconds": 900,
        "time": "00:15:00",
        "numberOfTimesRespondentsLeftQuestionPage": "1"
    },
    {
        "lastName": "Sagar",
        "firstName": "Saurav",
        "emailAddress": "sauravsagar19@gmail.com",
        "score": 2,
        "timeInSeconds": 900,
        "time": "00:15:00",
        "numberOfTimesRespondentsLeftQuestionPage": "0"
    },
    {
        "lastName": "Chauhan",
        "firstName": "Vishal",
        "emailAddress": "vchauhan76@gmail.com",
        "score": 1,
        "timeInSeconds": 900,
        "time": "00:15:00",
        "numberOfTimesRespondentsLeftQuestionPage": "0"
    },
    {
        "lastName": "Gurjar",
        "firstName": "Ashish",
        "emailAddress": "ashish32gurjar@gmail.com",
        "score": 0,
        "timeInSeconds": 900,
        "time": "00:15:00",
        "numberOfTimesRespondentsLeftQuestionPage": "3"
    },
    {
        "lastName": "Mishra",
        "firstName": "Shreyansh",
        "emailAddress": "shreyansh.mishra@increff.com",
        "score": 0,
        "timeInSeconds": 900,
        "time": "00:15:00",
        "numberOfTimesRespondentsLeftQuestionPage": "1"
    },
    {
        "lastName": "V",
        "firstName": "Dravid",
        "emailAddress": "dravid9071@gmail.com",
        "score": 0,
        "timeInSeconds": 900,
        "time": "00:15:00",
        "numberOfTimesRespondentsLeftQuestionPage": "0"
    },
    {
        "lastName": "Jaganathan",
        "firstName": "Lenin",
        "emailAddress": "lenijl18@gmail.com",
        "score": 0,
        "timeInSeconds": 900,
        "time": "00:15:00",
        "numberOfTimesRespondentsLeftQuestionPage": "0"
    },
    {
        "lastName": "Parwani",
        "firstName": "Dhiraj",
        "emailAddress": "dhiraj125@gmail.com",
        "score": 0,
        "timeInSeconds": 900,
        "time": "00:15:00",
        "numberOfTimesRespondentsLeftQuestionPage": "0"
    },
    {
        "lastName": "Kothari",
        "firstName": "Vijay",
        "emailAddress": "kotharipravesh2211@gmail.com",
        "score": 0,
        "timeInSeconds": 900,
        "time": "00:15:00",
        "numberOfTimesRespondentsLeftQuestionPage": "0"
    },
    {
        "lastName": "Kothari",
        "firstName": "Vijay",
        "emailAddress": "vijaykothari2211@gmail.com",
        "score": 0,
        "timeInSeconds": 900,
        "time": "00:15:00",
        "numberOfTimesRespondentsLeftQuestionPage": "0"
    },
    {
        "lastName": "Jain",
        "firstName": "Mayur",
        "emailAddress": "mayur.0210@gmail.com",
        "score": 0,
        "timeInSeconds": 900,
        "time": "00:15:00",
        "numberOfTimesRespondentsLeftQuestionPage": "0"
    },
    {
        "lastName": "Bm",
        "firstName": "Shilpa",
        "emailAddress": "Shilpabm.devops@gmail.com",
        "score": 0,
        "timeInSeconds": 900,
        "time": "00:15:00",
        "numberOfTimesRespondentsLeftQuestionPage": "0"
    },
    {
        "lastName": "Aryan",
        "firstName": "Arjun",
        "emailAddress": "arjunaryanrere@gmail.com",
        "score": 0,
        "timeInSeconds": 900,
        "time": "00:15:00",
        "numberOfTimesRespondentsLeftQuestionPage": "0"
    },
    {
        "lastName": "Jain",
        "firstName": "Aniket",
        "emailAddress": "aniket98jain@gmail.com",
        "score": 0,
        "timeInSeconds": 900,
        "time": "00:15:00",
        "numberOfTimesRespondentsLeftQuestionPage": "0"
    },
    {
        "lastName": "Awadhiya",
        "firstName": "Goutam",
        "emailAddress": "goutam.awadhiya@gmail.com",
        "score": 0,
        "timeInSeconds": 900,
        "time": "00:15:00",
        "numberOfTimesRespondentsLeftQuestionPage": "0"
    }
]
