[
    {
        "lastName": "Kumar",
        "firstName": "Abhay",
        "emailAddress": "kumarabhay1407@gmail.com",
        "score": 19,
        "timeInSeconds": 500,
        "time": "00:08:20",
        "numberOfTimesRespondentsLeftQuestionPage": "0"
    },
    {
        "lastName": "Mahajan",
        "firstName": "Ananya",
        "emailAddress": "ananya021311@gmail.com",
        "score": 19,
        "timeInSeconds": 535,
        "time": "00:08:55",
        "numberOfTimesRespondentsLeftQuestionPage": "0"
    },
    {
        "lastName": "Patel",
        "firstName": "Prashant",
        "emailAddress": "pmp@narola.email",
        "score": 19,
        "timeInSeconds": 576,
        "time": "00:09:36",
        "numberOfTimesRespondentsLeftQuestionPage": "1"
    },
    {
        "lastName": "Kumar",
        "firstName": "Satyam",
        "emailAddress": "skmuz00@gmail.com",
        "score": 19,
        "timeInSeconds": 895,
        "time": "00:14:55",
        "numberOfTimesRespondentsLeftQuestionPage": "0"
    },
    {
        "lastName": "Shah",
        "firstName": "Pratik",
        "emailAddress": "psh@narola.email",
        "score": 19,
        "timeInSeconds": 880,
        "time": "00:14:40",
        "numberOfTimesRespondentsLeftQuestionPage": "3"
    }
]
